kylinpy/__init__.py
kylinpy/exceptions.py
kylinpy/kylindb.py
kylinpy/kylinpy.py
kylinpy/logger.py
kylinpy/sqla_dialect.py
kylinpy/client/__init__.py
kylinpy/client/client.py
kylinpy/client/exceptions.py
kylinpy/datasource/__init__.py
kylinpy/datasource/_source_interface.py
kylinpy/datasource/cube_source.py
kylinpy/datasource/ke4_model_source.py
kylinpy/datasource/table_source.py
kylinpy/job/__init__.py
kylinpy/job/_job_interface.py
kylinpy/job/ke3_job_object.py
kylinpy/job/ke4_job_object.py
kylinpy/job/kylin_job_object.py
kylinpy/service/__init__.py
kylinpy/service/_service_interface.py
kylinpy/service/ke3_service.py
kylinpy/service/ke4_service.py
kylinpy/service/kylin_service.py
kylinpy/utils/__init__.py
kylinpy/utils/compat.py
kylinpy/utils/helper.py
kylinpy/utils/keywords.py
kylinpy/utils/kylin_types.py
kylinpy/utils/sqla_types.py
tests/__init__.py
tests/conftest.py
tests/test_client.py
tests/test_compat.py
tests/test_cube_source.py
tests/test_dialect.py
tests/test_ke3_service.py
tests/test_ke4_model_source.py
tests/test_ke4_service.py
tests/test_kylin_service.py
tests/test_kylin_types.py
tests/test_kylinpy.py
tests/test_sqla_types.py
tests/test_table_source.py
tests/fixtures/__init__.py
tests/fixtures/api.py
kylinpython-2.8.4.dist-info/LICENSE
kylinpython-2.8.4.dist-info/METADATA
kylinpython-2.8.4.dist-info/WHEEL
kylinpython-2.8.4.dist-info/entry_points.txt
kylinpython-2.8.4.dist-info/top_level.txt
kylinpython-2.8.4.dist-info/RECORD
