Metadata-Version: 2.1
Name: kylinpython
Version: 2.8.4
Summary: Apache Kylin Python Client Library with minor fixes
Home-page: https://github.com/jinyangzhen/kylinpy
Author: Yongjie Zhao
Author-email: yangzhen.jin@gmail.com
Maintainer: Yangzhen Jin
Maintainer-email: yangzhen.jin@gmail.com
License: MIT License
Keywords: apache kylin,kylin,kap,kyligence,kyligence enterprise,cli,sqlalchemy dialect
Platform: UNKNOWN
Classifier: Environment :: Console
Classifier: Intended Audience :: Developers
Classifier: License :: OSI Approved :: MIT License
Classifier: Operating System :: OS Independent
Classifier: Programming Language :: Python
Classifier: Programming Language :: Python :: 2.7
Classifier: Programming Language :: Python :: 3
Provides-Extra: sqlalchemy
Requires-Dist: sqlalchemy (>=1.1.0) ; extra == 'sqlalchemy'
